pilot_rules/__init__.py
pilot_rules/scaffolder.py
pilot_rules/guides/copilot.md
pilot_rules/guides/cursor.md
pilot_rules/templates/cursor/rules/auto-commit.mdc
pilot_rules/templates/cursor/rules/global-workflow.mdc
pilot_rules/templates/cursor/rules/init-project.mdc
pilot_rules/templates/cursor/rules/init-specs.mdc
pilot_rules/templates/cursor/rules/init-tasks.mdc
pilot_rules/templates/cursor/rules/specs-definition.mdc
pilot_rules/templates/cursor/rules/tasks-definition.mdc
pilot_rules/templates/github/copilot-instructions.md
pilot_rules/templates/github/prompts/init-project.prompt.md
pilot_rules/templates/github/prompts/init-specs.prompt.md
pilot_rules/templates/github/prompts/init-tasks.prompt.md
pilot_rules/templates/github/prompts/specs-definition.md
pilot_rules/templates/github/prompts/tasks-definition.md
pilot_rules-0.1.9.dist-info/METADATA
pilot_rules-0.1.9.dist-info/WHEEL
pilot_rules-0.1.9.dist-info/entry_points.txt
pilot_rules-0.1.9.dist-info/RECORD
